sudoku_game/__init__.py
sudoku_game/game.py
sudoku_game/game_ui.py
sudoku_game/main.py
play_sudoku-0.0.9.dist-info/METADATA
play_sudoku-0.0.9.dist-info/WHEEL
play_sudoku-0.0.9.dist-info/entry_points.txt
play_sudoku-0.0.9.dist-info/top_level.txt
play_sudoku-0.0.9.dist-info/RECORD
